<?xml version="1.0" encoding="UTF-8"?>
<ti:app xmlns:ti="http://ti.appcelerator.org">
    <property name="acs-oauth-secret-production" type="string">w8pPySK192t5gJRPzX9tcQWki3Ge7hTj</property>
    <property name="acs-oauth-key-production" type="string">bPsWhk9Jjbckl7Jhhjs20L8H9gikE9On</property>
    <property name="acs-api-key-production" type="string">QLDyS28IJXeiI6IVj7vDBaE57ZvTMCvb</property>
    <property name="acs-oauth-secret-development" type="string">omktmxrVsrb1DL0rHnaUF2Qnw0wZw8bl</property>
    <property name="acs-oauth-key-development" type="string">fJpL8ZoFQjvKkFRKmTZHDpABnrt8Bp8y</property>
    <property name="acs-api-key-development" type="string">2hpqq2L3H2rznzeuwznrHjq1ttxdT5HZ</property>
    <id>org.childrenofelements.mvp</id>
    <name>Children Of Elements</name>
    <version>1.0</version>
    <publisher>Children of elements</publisher>
    <url>http://childrenofelements.org</url>
    <description>Children of Elements</description>
    <copyright>2014 by children of elements</copyright>
    <icon>appicon.png</icon>
    <fullscreen>true</fullscreen>
    <navbar-hidden>true</navbar-hidden>
    <analytics>true</analytics>
    <guid>578fe5ff-2a7c-4724-8a29-d6d7ecfe8d81</guid>
    
    <ios>
        <property name="ti.ui.defaultunit"  type="string">dp</property>
        <plist>
            <dict>
                <key>UISupportedInterfaceOrientations~iphone</key>
                <array>
                    <string>UIInterfaceOrientationPortrait</string>
                </array>
                <key>UISupportedInterfaceOrientations~ipad</key>
                <array>
                    <string>UIInterfaceOrientationLandscapeLeft</string>
                    <string>UIInterfaceOrientationLandscapeRight</string>
                </array>
                <key>UIRequiresPersistentWiFi</key>
                <false/>
                <key>UIPrerenderedIcon</key>
                <false/>
                <key>UIStatusBarHidden</key>
                <false/>
                <key>UIStatusBarStyle</key>
                <string>UIStatusBarStyleDefault</string>
            </dict>
        </plist>
    </ios>
    <android xmlns:android="http://schemas.android.com/apk/res/android">
       
        <manifest>

            <application android:debuggable="false"
                android:icon="@drawable/appicon"
                android:label="Children Of Elements" android:name="ChildrenOfElementsApplication">
                <activity
                    android:configChanges="keyboardHidden|screenSize"
                    android:label="@string/app_name"
                    android:name=".ChildrenOfElementsActivity"
                    android:screenOrientation="landscape" android:theme="@style/Theme.Titanium">
                    <intent-filter>
                        <action android:name="android.intent.action.MAIN"/>
                        <category android:name="android.intent.category.LAUNCHER"/>
                    </intent-filter>
                </activity>
                <activity
                    android:configChanges="keyboardHidden|screenSize"
                    android:name="org.appcelerator.titanium.TiActivity" android:screenOrientation="landscape"/>
                <activity
                    android:configChanges="keyboardHidden|screenSize"
                    android:name="org.appcelerator.titanium.TiTranslucentActivity"
                    android:screenOrientation="landscape" android:theme="@android:style/Theme.Translucent"/>
                <activity android:configChanges="screenSize" android:name="ti.modules.titanium.ui.android.TiPreferencesActivity"/>
                <service android:exported="false" android:name="org.appcelerator.titanium.analytics.TiAnalyticsService"/>
            </application>
        </manifest>
    </android>
    <mobileweb>
        <precache/>
        <splash>
            <enabled>true</enabled>
            <inline-css-images>true</inline-css-images>
        </splash>
        <theme>default</theme>
    </mobileweb>
    <modules>
        <module platform="commonjs">ti.cloud</module>
    </modules>
    <deployment-targets>
        <target device="android">true</target>
        <target device="blackberry">false</target>
        <target device="ipad">true</target>
        <target device="iphone">false</target>
        <target device="mobileweb">false</target>
        <target device="tizen">false</target>
    </deployment-targets>
    <sdk-version>3.2.0.GA</sdk-version>
    <plugins>
        <plugin version="1.0">ti.alloy</plugin>
    </plugins>
</ti:app>
